SVSound/__init__.py
SVSound/levels.py
SVSound/sgwave.py
SVSound/wavefile.py
SVSound/recorders/AudioMoth.py
SVSound/recorders/__init__.py
SVSound/recorders/decimus.py
SVSound/recorders/generic.py
SVSound/recorders/icListen.py
SVSound/recorders/lars.py
SVSound/recorders/zoom.py
SVSound-0.3.4.dist-info/LICENSE
SVSound-0.3.4.dist-info/METADATA
SVSound-0.3.4.dist-info/WHEEL
SVSound-0.3.4.dist-info/top_level.txt
SVSound-0.3.4.dist-info/RECORD
