Metadata-Version: 2.1
Name: SVSound
Version: 0.3.4
Summary: A package to read Broadcast Wave files
Home-page: https://github.com/sprague252/SVSound
Author: Mark Sprague
Author-email: Mark Sprague <sprague252@gmail.com>
Project-URL: Homepage, https://github.com/sprague252/SVSound
Project-URL: Issues, https://github.com/sprague252/SVSound/issues
Classifier: Programming Language :: Python :: 3
Classifier: License :: OSI Approved :: GNU General Public License v3 (GPLv3)
Classifier: Operating System :: OS Independent
Requires-Python: >=3.9
License-File: LICENSE
Requires-Dist: numpy
Requires-Dist: scipy
Requires-Dist: tables
